academic_metrics/__init__.py
academic_metrics/AI/__init__.py
academic_metrics/AI/abstract_classifier.py
academic_metrics/ChainBuilder/ChainBuilder.py
academic_metrics/ChainBuilder/__init__.py
academic_metrics/DB/DatabaseSetup.py
academic_metrics/DB/__init__.py
academic_metrics/DB/article_to_excel.py
academic_metrics/DB/clear_db.py
academic_metrics/DB/get_all_data.py
academic_metrics/ai_data_models/__init__.py
academic_metrics/ai_data_models/ai_pydantic_models.py
academic_metrics/ai_prompts/__init__.py
academic_metrics/ai_prompts/abstract_summary_prompts.py
academic_metrics/ai_prompts/classification_prompts.py
academic_metrics/ai_prompts/human_prompt.py
academic_metrics/ai_prompts/method_prompts.py
academic_metrics/ai_prompts/sentence_analysis_prompts.py
academic_metrics/ai_prompts/theme_prompts.py
academic_metrics/configs/__init__.py
academic_metrics/configs/global_config.py
academic_metrics/constants/__init__.py
academic_metrics/constants/dir_paths.py
academic_metrics/core/__init__.py
academic_metrics/core/category_processor.py
academic_metrics/data_collection/CrossrefWrapper.py
academic_metrics/data_collection/__init__.py
academic_metrics/data_collection/scraper.py
academic_metrics/dataclass_models/__init__.py
academic_metrics/dataclass_models/abstract_base_dataclass.py
academic_metrics/dataclass_models/concrete_dataclasses.py
academic_metrics/dataclass_models/string_variation.py
academic_metrics/enums/__init__.py
academic_metrics/enums/dataclass_enums.py
academic_metrics/enums/enums.py
academic_metrics/factories/__init__.py
academic_metrics/factories/abstract_classifier_factory.py
academic_metrics/factories/dataclass_factory.py
academic_metrics/factories/strategy_factory.py
academic_metrics/mapping/_AbstractCategoryMap.py
academic_metrics/mapping/__init__.py
academic_metrics/orchestrators/__init__.py
academic_metrics/orchestrators/category_data_orchestrator.py
academic_metrics/orchestrators/classification_orchestrator.py
academic_metrics/other/__init__.py
academic_metrics-1.0.99.dist-info/METADATA
academic_metrics-1.0.99.dist-info/WHEEL
academic_metrics-1.0.99.dist-info/top_level.txt
academic_metrics-1.0.99.dist-info/RECORD
