Metadata-Version: 2.2
Name: academic_metrics
Version: 1.0.99
Summary: A tool to extract and format academic data from Web of Science and Crossref
Author-email: Spencer Presley <spencerpresley96@gmail.com>, Cole Barbes <cbarbes1@gulls.salisbury.edu>
Project-URL: Homepage, https://github.com/SpencerPresley/AcademicMetrics
Project-URL: Bug Tracker, https://github.com/SpencerPresley/AcademicMetrics/issues
Classifier: Programming Language :: Python :: 3
Classifier: License :: OSI Approved :: MIT License
Classifier: Operating System :: OS Independent
Requires-Python: >=3.9
Requires-Dist: aiohttp==3.10.8
Requires-Dist: beautifulsoup4==4.12.3
Requires-Dist: langchain==0.3.7
Requires-Dist: langchain_anthropic==0.3.0
Requires-Dist: langchain_core==0.3.19
Requires-Dist: langchain_google_genai==2.0.5
Requires-Dist: langchain_openai==0.2.9
Requires-Dist: openai==1.58.1
Requires-Dist: pandas==2.2.3
Requires-Dist: pydantic==2.9.2
Requires-Dist: pylatexenc==2.10
Requires-Dist: pymongo==4.10.1
Requires-Dist: python-dotenv==1.0.1
Requires-Dist: selenium==4.26.1
Requires-Dist: Unidecode==1.3.8
Requires-Dist: platformdirs==4.3.6
Requires-Dist: webdriver_manager==4.0.2
Requires-Dist: lxml==5.3.0
Requires-Dist: openpyxl==3.1.5
Provides-Extra: docs
Requires-Dist: sphinx; extra == "docs"
Requires-Dist: piccolo-theme; extra == "docs"
Requires-Dist: sphinx-autodoc-typehints; extra == "docs"
Requires-Dist: pydata-sphinx-theme; extra == "docs"
